mecabwrap/__init__.py
mecabwrap/api.py
mecabwrap/config.py
mecabwrap/domecab.py
mecabwrap/utils.py
mecabwrap-0.3.4.dist-info/LICENSE.txt
mecabwrap-0.3.4.dist-info/METADATA
mecabwrap-0.3.4.dist-info/WHEEL
mecabwrap-0.3.4.dist-info/top_level.txt
mecabwrap-0.3.4.dist-info/RECORD
