Metadata-Version: 2.1
Name: mecabwrap
Version: 0.3.4
Summary: Yet another interface to MeCab morphological analyzer
Home-page: https://github.com/kota7/mecabwrap-py
Author: Kota Mori
Author-email: kmori05@gmail.com
License: UNKNOWN
Download-URL: https://github.com/kota7/mecabwrap-py/archive/0.1.5.tar.gz
Platform: UNKNOWN
Classifier: Development Status :: 3 - Alpha
Classifier: Natural Language :: Japanese
Classifier: License :: OSI Approved :: MIT License
Classifier: Programming Language :: Python :: 2.7
Classifier: Programming Language :: Python :: 3.4
Classifier: Programming Language :: Python :: 3.5
Classifier: Programming Language :: Python :: 3.6
Classifier: Programming Language :: Python :: 3.7
Classifier: Programming Language :: Python :: 3.8
